mealgenerator/__init__.py
mealgenerator/mealgenerator.py
mealgenerator_Rhyknowscerious-2019.9.29.7.dist-info/LICENSE
mealgenerator_Rhyknowscerious-2019.9.29.7.dist-info/METADATA
mealgenerator_Rhyknowscerious-2019.9.29.7.dist-info/WHEEL
mealgenerator_Rhyknowscerious-2019.9.29.7.dist-info/top_level.txt
mealgenerator_Rhyknowscerious-2019.9.29.7.dist-info/RECORD
