Metadata-Version: 2.1
Name: mealgenerator-Rhyknowscerious
Version: 2019.9.29.7
Summary: Generates random meals for meal planning.
Home-page: https://bitbucket.org/Rhyknowscerious/mealgenerator.py/
Author: Ryan James Decker
Author-email: email@iamryanjdecker.com
License: UNKNOWN
Platform: UNKNOWN
Classifier: Programming Language :: Python :: 2
Classifier: License :: OSI Approved :: Mozilla Public License 2.0 (MPL 2.0)
Classifier: Operating System :: POSIX :: Linux
Requires-Python: >=2.7,<3.0
